tsv_calendar/__init__.py
tsv_calendar-2022.12.14.dist-info/LICENSE.txt
tsv_calendar-2022.12.14.dist-info/METADATA
tsv_calendar-2022.12.14.dist-info/WHEEL
tsv_calendar-2022.12.14.dist-info/top_level.txt
tsv_calendar-2022.12.14.dist-info/RECORD
