Metadata-Version: 2.1
Name: tsv-calendar
Version: 2022.12.14
Summary: TSV Reader for bunzbar Project
Author: TheStegosaurus_
Classifier: Programming Language :: Python :: 3
Classifier: License :: OSI Approved :: GNU General Public License v3 (GPLv3)
Classifier: Operating System :: OS Independent
Classifier: Development Status :: 3 - Alpha
License-File: LICENSE.txt
